{
    "title": "一个孩子的星星梦",
    "author": "狄更斯",
    "content": "<p>“从前有一个小男孩，漫步山间田野，四处游荡闲逛，脑子里想着各种各样的事情。他有个姐姐，也是个小孩子，是他形影相随的亲密伙伴。他们常常终日神思遐想，对一切充满好奇。他们惊叹花的美丽，惊叹天空的高远和蔚蓝，惊叹明媚河水的幽深，惊叹上帝——这个可爱世界的缔造者——的仁慈和力量。 </p>\n<p>他们常常互相问询：‘如果有那么一天，假使世界上的孩子都死了，花和水还有天空，它们会感到难过吗？’他们坚信，它们会感到难过的。‘因为’他们认为，‘蓓蕾是花的孩子，山谷里奔腾的欢快的小溪是河水的孩子；通宵在天空中玩捉迷藏的那些最小的光点，想必是星星的孩子；当它们再也找不到自己的伙伴——人类的孩子，它们肯定都会伤心的。’ </p>\n<p>每天晚上，在教堂尖顶附近，墓地的上空，就会有一颗闪灵的星星先于其他星星，出现在夜空。在他们的眼里，它比其他所有的星星都更大更美。每天夜晚，他们都手拉手站在窗前守候着它。无论谁先看到那颗星星，都会大喊道：‘我看见星星啦！’而通常的情形是，他们会齐声喊将起来，因为他们太熟悉它升起的时间和地方了。渐渐的，他们和那颗星星成了及其要好的朋友；每天就寝之前，他们都要向窗外再张望一眼，向星星道晚安；当他们转身准备入睡时，就会念上一句：‘上帝保佑星星！’ </p>\n<p>可是，在那样幼小的年纪，哦，非常非常小的年纪，他们的姐姐就枯萎憔悴了。她变得太虚弱了，以及不再可能夜里站在窗前，于是哪个男孩忧伤地独自望着窗外。每当他看到了那颗星星，他会转过身来对着床上那张苍白的面孔说道：‘我看见星星啦！’这时，一丝微笑会浮现在她的脸上，一个微弱的声音答道：‘上帝保佑我的弟弟和星星！’ </p>\n<p>不久，不幸的时刻来临了，一切都来的那么突然！从此男孩独自一人望着窗外；从此床上不再有任何面庞；从此墓地中多了一个从前没有的小小的坟墓，每当他泪眼婆娑的望着那颗星星，星星无垠的光芒照耀在他的身上。 </p>\n<p>如今，这些光芒是那样地明亮，似乎铺就了一条从人间通往天堂的金光大道，当男孩孤独地睡在自己床上，他梦见了那颗星星，他梦见自己躺在窗上，看见一对人在天使的引领下走上了那条金光大道。那颗星星四敞大开着，一个光明神圣的世界展现在他的面前，许多这样的天使在那里迎候他们。 </p>\n<p>所有这些在此等候的天使，用它们愉快的目光注视着那些被带到星星上来的人们。有些天使从他们站着的长长队列中出来，落到人们的脖子上，温柔地亲吻着，然后和他们一起沿着星光大道离开，他们在一起无比开心，小男孩躺在床上，高兴得哭了。 </p>\n<p>但有许多天使并没有和他们一起离开，其中有一张小男孩非常熟悉的面孔，那张曾经病恹恹地躺在床上的面孔，如今已变得容光焕发，光彩照人，然而他的确能够在天国所有的主人中找出他的姐姐。 </p>\n<p>他的天使姐姐在星星的入口处徘徊不前，逗留不去，问那位把人们带到彼岸来的天使长:‘我的弟弟来了吗？’ </p>\n<p>天使长答道‘没有。’ </p>\n<p>她满怀希望的转身，准备离去，小男孩连忙伸出手臂喊道：‘噢，姐姐，我在这儿呢！带我走吧！’于是她转头朝小男孩看去，含笑的目光落在他的身上，然后，一切便陷入黑暗。星光在房间里闪耀，当他泪眼婆娑地望着那颗星星，星星无垠的光芒照耀在他身上。 </p>\n<p>从那次后，小男孩每次看到那颗星星，犹如看到自己大限来临时要回的家。他认为，自己不但属于尘世，也属于那颗星星，因为他的天使姐姐已经去了那里。 </p>\n<p>一个婴儿诞生了，小男孩添了一个弟弟。他是那么小，还从未说过一句话，在床上伸展着小胳膊小腿儿，死了。 </p>\n<p>　　 </p>\n<p> </p>\n<p>　　 </p>\n<p> </p>\n<p>　　 </p>\n<p>　　 </p>\n<p> </p>\n<p> </p>\n<p>　　 </p>\n<p> </p>\n<p>　　 </p>\n<p> </p>\n<p> </p>\n<p>　　 </p>\n<p>　　 </p>\n<p>　　 </p>\n<p>　　 </p>\n<p>　　 </p>\n<p>　　 </p>\n<p> </p>\n<p>　　 </p>\n<p> </p>\n<p> （温哲仙　译）</p>",
    "text_num": 1488,
    "date": "2020-07-07 10:10",
    "content_hash": "1686cc7a0362e01cad3f0e375dade72c4996c729a84a613b13a099130fcc98eb"
}