{
    "title": "一条路",
    "author": "亦舒",
    "content": "<p>连我这样年纪的人，都认为女性其实只有一条路可走，那就是先搞身心经济独立，然后才决定是否要成家立业，希望工作可与家庭并重。 </p>\n<p>不知恁地，年轻一大截的小朋友却表示渴望做金丝雀，受保护、被宠爱、一生毋需挣扎，生活有人照顾。 </p>\n<p>那是另外一个世界，另外一种营生，在这地球上，每一件事都有阴暗面，我们生活在一个真实的世界里，没有什么，毋需要付出代价。 </p>\n<p>工作所需付出的精神时间心血，完全没有秘密可言，光明正大：竞争、失败、再起、成功、升上去、努力、获得报酬、达到目的。 </p>\n<p>那另外一种营生，黑幕实在不足为外人道，亦是一条血路，一般是一将功成万骨枯，我们所见到的，只是状元花魁的表面风光，一个人要长期在另一个人手中讨生活，无论如何是痛苦的。那一行沦落起来，又可达万劫不复地步，不如自力更生，工作能力一旦获得社会赏识，则要名有名，要利有利，自信十足，顾盼自如。 </p>\n<p>那么多妇女放弃老路不走去走新路，可见老路上自有不可告人之荆棘，而新路亦自有可喜之处。</p>",
    "text_num": 415,
    "date": "2020-10-30 03:40",
    "content_hash": "c8c20b512d6a961ed41555e73fef32a33bf5a789fcf11d0a580fa43a3ce5baa9"
}